adblock/__init__.py
adblock_hosts-2.1.dist-info/LICENSE
adblock_hosts-2.1.dist-info/METADATA
adblock_hosts-2.1.dist-info/WHEEL
adblock_hosts-2.1.dist-info/entry_points.txt
adblock_hosts-2.1.dist-info/top_level.txt
adblock_hosts-2.1.dist-info/RECORD
