Metadata-Version: 2.1
Name: adblock-hosts
Version: 2.1
Summary: Automatically fetch and merge adblock hosts.
Home-page: UNKNOWN
Author: Keane O'Kelley
Author-email: dev@keane.space
License: MIT
Platform: UNKNOWN
Requires-Dist: requests-futures
Requires-Dist: PyYAML
Requires-Dist: pytest
